{
  "team_id": 0,
  "team_name": "Liverpool",
  "standings": {
    "position": 1,
    "team_id": 0,
    "team_name": "Arsenal",
    "played": 38,
    "won": 26.0,
    "drawn": 12.0,
    "lost": 0.0,
    "points": 90.0,
    "goals_for": 73.0,
    "goals_against": 26.0,
    "goal_difference": 47.0,
    "win_rate": 68.4,
    "points_pct": 78.9,
    "goals_per_game": 1.92,
    "goals_conceded_per_game": 0.68
  },
  "matches": [
    {
      "match_id": 3749257,
      "matchday": 38,
      "match_date": "2004-05-15 00:00:00",
      "home_team_id": 0,
      "home_team_name": "Arsenal",
      "away_team_id": 0,
      "away_team_name": "Leicester City",
      "home_score": 2,
      "away_score": 1,
      "winner": "HOME_TEAM",
      "match_status": "available",
      "home_result": "W",
      "away_result": "L"
    },
    {
      "match_id": 3749603,
      "matchday": 2,
      "match_date": "2004-05-09 00:00:00",
      "home_team_id": 0,
      "home_team_name": "Fulham",
      "away_team_id": 0,
      "away_team_name": "Arsenal",
      "home_score": 0,
      "away_score": 1,
      "winner": "AWAY_TEAM",
      "match_status": "available",
      "home_result": "L",
      "away_result": "W"
    },
    {
      "match_id": 3749274,
      "matchday": 2,
      "match_date": "2004-05-04 00:00:00",
      "home_team_id": 0,
      "home_team_name": "Portsmouth",
      "away_team_id": 0,
      "away_team_name": "Arsenal",
      "home_score": 1,
      "away_score": 1,
      "winner": "DRAW",
      "match_status": "available",
      "home_result": "D",
      "away_result": "D"
    },
    {
      "match_id": 3749462,
      "matchday": 35,
      "match_date": "2004-05-01 00:00:00",
      "home_team_id": 0,
      "home_team_name": "Arsenal",
      "away_team_id": 0,
      "away_team_name": "Birmingham City",
      "home_score": 0,
      "away_score": 0,
      "winner": "DRAW",
      "match_status": "available",
      "home_result": "D",
      "away_result": "D"
    },
    {
      "match_id": 3749068,
      "matchday": 2,
      "match_date": "2004-04-25 00:00:00",
      "home_team_id": 0,
      "home_team_name": "Tottenham Hotspur",
      "away_team_id": 0,
      "away_team_name": "Arsenal",
      "home_score": 2,
      "away_score": 2,
      "winner": "DRAW",
      "match_status": "available",
      "home_result": "D",
      "away_result": "D"
    },
    {
      "match_id": 3749453,
      "matchday": 33,
      "match_date": "2004-04-16 00:00:00",
      "home_team_id": 0,
      "home_team_name": "Arsenal",
      "away_team_id": 0,
      "away_team_name": "Leeds United",
      "home_score": 5,
      "away_score": 0,
      "winner": "HOME_TEAM",
      "match_status": "available",
      "home_result": "W",
      "away_result": "L"
    },
    {
      "match_id": 3749431,
      "matchday": 2,
      "match_date": "2004-04-11 00:00:00",
      "home_team_id": 0,
      "home_team_name": "Newcastle United",
      "away_team_id": 0,
      "away_team_name": "Arsenal",
      "home_score": 0,
      "away_score": 0,
      "winner": "DRAW",
      "match_status": "available",
      "home_result": "D",
      "away_result": "D"
    },
    {
      "match_id": 3749448,
      "matchday": 31,
      "match_date": "2004-04-09 00:00:00",
      "home_team_id": 0,
      "home_team_name": "Arsenal",
      "away_team_id": 0,
      "away_team_name": "Liverpool",
      "home_score": 4,
      "away_score": 2,
      "winner": "HOME_TEAM",
      "match_status": "available",
      "home_result": "W",
      "away_result": "L"
    },
    {
      "match_id": 3749246,
      "matchday": 30,
      "match_date": "2004-03-28 00:00:00",
      "home_team_id": 0,
      "home_team_name": "Arsenal",
      "away_team_id": 0,
      "away_team_name": "Manchester United",
      "home_score": 1,
      "away_score": 1,
      "winner": "DRAW",
      "match_status": "available",
      "home_result": "D",
      "away_result": "D"
    },
    {
      "match_id": 3749403,
      "matchday": 29,
      "match_date": "2004-03-20 00:00:00",
      "home_team_id": 0,
      "home_team_name": "Arsenal",
      "away_team_id": 0,
      "away_team_name": "Bolton Wanderers",
      "home_score": 2,
      "away_score": 1,
      "winner": "HOME_TEAM",
      "match_status": "available",
      "home_result": "W",
      "away_result": "L"
    },
    {
      "match_id": 3749465,
      "matchday": 2,
      "match_date": "2004-03-13 00:00:00",
      "home_team_id": 0,
      "home_team_name": "Blackburn Rovers",
      "away_team_id": 0,
      "away_team_name": "Arsenal",
      "home_score": 0,
      "away_score": 2,
      "winner": "AWAY_TEAM",
      "match_status": "available",
      "home_result": "L",
      "away_result": "W"
    },
    {
      "match_id": 3749642,
      "matchday": 27,
      "match_date": "2004-02-28 00:00:00",
      "home_team_id": 0,
      "home_team_name": "Arsenal",
      "away_team_id": 0,
      "away_team_name": "Charlton Athletic",
      "home_score": 2,
      "away_score": 1,
      "winner": "HOME_TEAM",
      "match_status": "available",
      "home_result": "W",
      "away_result": "L"
    },
    {
      "match_id": 3749276,
      "matchday": 2,
      "match_date": "2004-02-21 00:00:00",
      "home_team_id": 0,
      "home_team_name": "Chelsea",
      "away_team_id": 0,
      "away_team_name": "Arsenal",
      "home_score": 1,
      "away_score": 2,
      "winner": "AWAY_TEAM",
      "match_status": "available",
      "home_result": "L",
      "away_result": "W"
    },
    {
      "match_id": 3749631,
      "matchday": 25,
      "match_date": "2004-02-10 00:00:00",
      "home_team_id": 0,
      "home_team_name": "Arsenal",
      "away_team_id": 0,
      "away_team_name": "Southampton",
      "home_score": 2,
      "away_score": 0,
      "winner": "HOME_TEAM",
      "match_status": "available",
      "home_result": "W",
      "away_result": "L"
    },
    {
      "match_id": 3749052,
      "matchday": 2,
      "match_date": "2004-02-07 00:00:00",
      "home_team_id": 0,
      "home_team_name": "Wolverhampton Wanderers",
      "away_team_id": 0,
      "away_team_name": "Arsenal",
      "home_score": 1,
      "away_score": 3,
      "winner": "AWAY_TEAM",
      "match_status": "available",
      "home_result": "L",
      "away_result": "W"
    },
    {
      "match_id": 3749233,
      "matchday": 23,
      "match_date": "2004-02-01 00:00:00",
      "home_team_id": 0,
      "home_team_name": "Arsenal",
      "away_team_id": 0,
      "away_team_name": "Manchester City",
      "home_score": 2,
      "away_score": 1,
      "winner": "HOME_TEAM",
      "match_status": "available",
      "home_result": "W",
      "away_result": "L"
    },
    {
      "match_id": 3749133,
      "matchday": 2,
      "match_date": "2004-01-18 00:00:00",
      "home_team_id": 0,
      "home_team_name": "Aston Villa",
      "away_team_id": 0,
      "away_team_name": "Arsenal",
      "home_score": 0,
      "away_score": 2,
      "winner": "AWAY_TEAM",
      "match_status": "available",
      "home_result": "L",
      "away_result": "W"
    },
    {
      "match_id": 3749153,
      "matchday": 21,
      "match_date": "2004-01-10 00:00:00",
      "home_team_id": 0,
      "home_team_name": "Arsenal",
      "away_team_id": 0,
      "away_team_name": "Middlesbrough",
      "home_score": 4,
      "away_score": 1,
      "winner": "HOME_TEAM",
      "match_status": "available",
      "home_result": "W",
      "away_result": "L"
    },
    {
      "match_id": 3749117,
      "matchday": 2,
      "match_date": "2004-01-07 00:00:00",
      "home_team_id": 0,
      "home_team_name": "Everton",
      "away_team_id": 0,
      "away_team_name": "Arsenal",
      "home_score": 1,
      "away_score": 1,
      "winner": "DRAW",
      "match_status": "available",
      "home_result": "D",
      "away_result": "D"
    },
    {
      "match_id": 3749310,
      "matchday": 1,
      "match_date": "2003-12-29 00:00:00",
      "home_team_id": 0,
      "home_team_name": "Southampton",
      "away_team_id": 0,
      "away_team_name": "Arsenal",
      "home_score": 0,
      "away_score": 1,
      "winner": "AWAY_TEAM",
      "match_status": "available",
      "home_result": "L",
      "away_result": "W"
    },
    {
      "match_id": 3749522,
      "matchday": 18,
      "match_date": "2003-12-26 00:00:00",
      "home_team_id": 0,
      "home_team_name": "Arsenal",
      "away_team_id": 0,
      "away_team_name": "Wolverhampton Wanderers",
      "home_score": 3,
      "away_score": 0,
      "winner": "HOME_TEAM",
      "match_status": "available",
      "home_result": "W",
      "away_result": "L"
    },
    {
      "match_id": 3749278,
      "matchday": 1,
      "match_date": "2003-12-20 00:00:00",
      "home_team_id": 0,
      "home_team_name": "Bolton Wanderers",
      "away_team_id": 0,
      "away_team_name": "Arsenal",
      "home_score": 1,
      "away_score": 1,
      "winner": "DRAW",
      "match_status": "available",
      "home_result": "D",
      "away_result": "D"
    },
    {
      "match_id": 3749360,
      "matchday": 16,
      "match_date": "2003-12-14 00:00:00",
      "home_team_id": 0,
      "home_team_name": "Arsenal",
      "away_team_id": 0,
      "away_team_name": "Blackburn Rovers",
      "home_score": 1,
      "away_score": 0,
      "winner": "HOME_TEAM",
      "match_status": "available",
      "home_result": "W",
      "away_result": "L"
    },
    {
      "match_id": 3749590,
      "matchday": 1,
      "match_date": "2003-12-06 00:00:00",
      "home_team_id": 0,
      "home_team_name": "Leicester City",
      "away_team_id": 0,
      "away_team_name": "Arsenal",
      "home_score": 1,
      "away_score": 1,
      "winner": "DRAW",
      "match_status": "available",
      "home_result": "D",
      "away_result": "D"
    },
    {
      "match_id": 3749192,
      "matchday": 14,
      "match_date": "2003-11-30 00:00:00",
      "home_team_id": 0,
      "home_team_name": "Arsenal",
      "away_team_id": 0,
      "away_team_name": "Fulham",
      "home_score": 0,
      "away_score": 0,
      "winner": "DRAW",
      "match_status": "available",
      "home_result": "D",
      "away_result": "D"
    },
    {
      "match_id": 3749434,
      "matchday": 1,
      "match_date": "2003-11-22 00:00:00",
      "home_team_id": 0,
      "home_team_name": "Birmingham City",
      "away_team_id": 0,
      "away_team_name": "Arsenal",
      "home_score": 0,
      "away_score": 3,
      "winner": "AWAY_TEAM",
      "match_status": "available",
      "home_result": "L",
      "away_result": "W"
    },
    {
      "match_id": 3749196,
      "matchday": 12,
      "match_date": "2003-11-08 00:00:00",
      "home_team_id": 0,
      "home_team_name": "Arsenal",
      "away_team_id": 0,
      "away_team_name": "Tottenham Hotspur",
      "home_score": 2,
      "away_score": 1,
      "winner": "HOME_TEAM",
      "match_status": "available",
      "home_result": "W",
      "away_result": "L"
    },
    {
      "match_id": 3749346,
      "matchday": 1,
      "match_date": "2003-11-01 00:00:00",
      "home_team_id": 0,
      "home_team_name": "Leeds United",
      "away_team_id": 0,
      "away_team_name": "Arsenal",
      "home_score": 1,
      "away_score": 4,
      "winner": "AWAY_TEAM",
      "match_status": "available",
      "home_result": "L",
      "away_result": "W"
    },
    {
      "match_id": 3749526,
      "matchday": 1,
      "match_date": "2003-10-26 00:00:00",
      "home_team_id": 0,
      "home_team_name": "Charlton Athletic",
      "away_team_id": 0,
      "away_team_name": "Arsenal",
      "home_score": 1,
      "away_score": 1,
      "winner": "DRAW",
      "match_status": "available",
      "home_result": "D",
      "away_result": "D"
    },
    {
      "match_id": 3749079,
      "matchday": 9,
      "match_date": "2003-10-18 00:00:00",
      "home_team_id": 0,
      "home_team_name": "Arsenal",
      "away_team_id": 0,
      "away_team_name": "Chelsea",
      "home_score": 2,
      "away_score": 1,
      "winner": "HOME_TEAM",
      "match_status": "available",
      "home_result": "W",
      "away_result": "L"
    },
    {
      "match_id": 3749253,
      "matchday": 1,
      "match_date": "2003-10-04 00:00:00",
      "home_team_id": 0,
      "home_team_name": "Liverpool",
      "away_team_id": 0,
      "away_team_name": "Arsenal",
      "home_score": 1,
      "away_score": 2,
      "winner": "AWAY_TEAM",
      "match_status": "available",
      "home_result": "L",
      "away_result": "W"
    },
    {
      "match_id": 3749528,
      "matchday": 7,
      "match_date": "2003-09-26 00:00:00",
      "home_team_id": 0,
      "home_team_name": "Arsenal",
      "away_team_id": 0,
      "away_team_name": "Newcastle United",
      "home_score": 3,
      "away_score": 2,
      "winner": "HOME_TEAM",
      "match_status": "available",
      "home_result": "W",
      "away_result": "L"
    },
    {
      "match_id": 3749552,
      "matchday": 1,
      "match_date": "2003-09-21 00:00:00",
      "home_team_id": 0,
      "home_team_name": "Manchester United",
      "away_team_id": 0,
      "away_team_name": "Arsenal",
      "home_score": 0,
      "away_score": 0,
      "winner": "DRAW",
      "match_status": "available",
      "home_result": "D",
      "away_result": "D"
    },
    {
      "match_id": 3749296,
      "matchday": 5,
      "match_date": "2003-09-13 00:00:00",
      "home_team_id": 0,
      "home_team_name": "Arsenal",
      "away_team_id": 0,
      "away_team_name": "Portsmouth",
      "home_score": 1,
      "away_score": 1,
      "winner": "DRAW",
      "match_status": "available",
      "home_result": "D",
      "away_result": "D"
    },
    {
      "match_id": 3749454,
      "matchday": 1,
      "match_date": "2003-08-31 00:00:00",
      "home_team_id": 0,
      "home_team_name": "Manchester City",
      "away_team_id": 0,
      "away_team_name": "Arsenal",
      "home_score": 1,
      "away_score": 2,
      "winner": "AWAY_TEAM",
      "match_status": "available",
      "home_result": "L",
      "away_result": "W"
    },
    {
      "match_id": 3749108,
      "matchday": 3,
      "match_date": "2003-08-27 00:00:00",
      "home_team_id": 0,
      "home_team_name": "Arsenal",
      "away_team_id": 0,
      "away_team_name": "Aston Villa",
      "home_score": 2,
      "away_score": 0,
      "winner": "HOME_TEAM",
      "match_status": "available",
      "home_result": "W",
      "away_result": "L"
    },
    {
      "match_id": 3749358,
      "matchday": 1,
      "match_date": "2003-08-24 00:00:00",
      "home_team_id": 0,
      "home_team_name": "Middlesbrough",
      "away_team_id": 0,
      "away_team_name": "Arsenal",
      "home_score": 0,
      "away_score": 4,
      "winner": "AWAY_TEAM",
      "match_status": "available",
      "home_result": "L",
      "away_result": "W"
    },
    {
      "match_id": 3749493,
      "matchday": 1,
      "match_date": "2003-08-16 00:00:00",
      "home_team_id": 0,
      "home_team_name": "Arsenal",
      "away_team_id": 0,
      "away_team_name": "Everton",
      "home_score": 2,
      "away_score": 1,
      "winner": "HOME_TEAM",
      "match_status": "available",
      "home_result": "W",
      "away_result": "L"
    }
  ]
}